{
  "name": "Responda Se Puder",
  "uri": "respondasepuder",
  "version": 1,
  "tasks": [
    {
      "name": "Banco de Questões",
      "uri": "question",
      "description": "Criar/editar/selecionar um banco de questões para o jogo.",
      "type": "text_database",
      "dependencies": null,
      "outputs": [
        {
          "name": "pergFacil.json",
          "type": "json",
          "path": ""
        },
        {
          "name": "pergMedio.json",
          "type": "json",
          "path": ""
        },
        {
          "name": "pergDificil.json",
          "type": "json",
          "path": ""
        }
      ]
    }

  ],
  "outputs": [
    "web"
  ],
  "vars": {
    "width": 800,
    "height": 600
  }
}